{"timestamp":"2026-01-28T22:19:58.525006+04:00","supplier":"Arabian Oryx","apiName":"HotelRates","url":"http://uat-apiv2.giinfotech.ae/api/v2/hotel/RoomDetails","method":"POST","headers":{"Apikey":["R5LLulyAFEiaS76V9AOgSa=="],"Content-Type":["application/json; charset=utf-8"]},"queryParams":{},"requestBody":{"SessionId":"2d13510ee640445db98d43b1ac4a2e43","SearchParameter":{"HotelCode":"61461","Currency":"AED","Rooms":{"Room":[{"RoomIdentifier":1,"Adult":2},{"RoomIdentifier":2,"Adult":2}]}}},"curlCommand":"curl -X POST -H 'Apikey: R5LLulyAFEiaS76V9AOgSa==' -H 'Content-Type: application/json; charset=utf-8' 'http://uat-apiv2.giinfotech.ae/api/v2/hotel/RoomDetails' -d '{\"SessionId\":\"2d13510ee640445db98d43b1ac4a2e43\",\"SearchParameter\":{\"HotelCode\":\"61461\",\"Currency\":\"AED\",\"Rooms\":{\"Room\":[{\"RoomIdentifier\":1,\"Adult\":2},{\"RoomIdentifier\":2,\"Adult\":2}]}}}'","response":{"statusCode":200,"headers":{"Content-Type":["application/json; charset=utf-8"],"Server":["Microsoft-IIS/10.0"],"X-Powered-By":["ASP.NET"],"Date":["Wed, 28 Jan 2026 18:19:59 GMT"]},"body":{"errorInfo":null,"generalInfo":{"apiKey":"R5LLulyAFEiaS76V9AOgSa==","customerCode":null,"sessionId":"2d13510ee640445db98d43b1ac4a2e43","timeStamp":"2026-01-28T22:19:58Z"},"monetary":{"currency":{"code":"AED","exchangeRate":0.274,"text":"AED"}},"hotel":{"supplierShortCode":null,"minPrice":null,"hotelInfo":{"code":"61461","lcSupplier":"","starRating":"3","lat":"25.22283533238","lon":"55.285807549954","add2":"P.O. Box 9544 , Dubai","city":"Dubai","spHotelCode":"","lcHotelCode":"","name":"ibis World Trade Centre Dubai","image":"https://static.giinfotech.ae/medianew/thumbnail/61461/Primaryimage_51f55adf_z.jpg","description":"","add1":"Sheikh Zayed Road"},"code":"61461","supplierCurrency":null,"supplierMinPrice":null,"rooms":{"room":[{"isCancelationPolicyAvailble":true,"inclusions":[{"type":"Inclusion","text":"Room Only"}],"price":{"isDynamic":false,"promotions":null,"supplierExtraBedPrice":0,"taxType":null,"commission":0,"discount":null,"priceBreakdownRules":null,"gross":373.01,"isPackage":false,"isExclusiveRate":false,"supplierGross":373.01,"supplierNet":373.01,"supplierCommission":0,"net":373.01,"supplierCurrency":"AED","supplierTax":0,"currency":null,"tax":0,"extraBedPrice":0,"isB2C":false},"sMeal":"Room_Only","contractType":"O","shortCode":"ArabianOryx","isPriceBreakupAvailable":true,"policies":null,"spHotelCode":null,"roomCombinationId":1831,"minStay":null,"bedTypes":null,"roomIdentifier":1,"marriageIdentifier":1831,"meal":"Room Only","status":"Available","group":null,"extraBedCount":null,"adult":2,"guests":null,"mealCode":"RO","rateKey":"1082519!TB!12!TB!84df4dff-fc73-11f0-822a-b62521cc9858!TB!N!TB!AFF!|1O","supplierGroupCode":183,"mealDescription":"Room Only","groupCode":175,"isCache":false,"remarks":{"remark":[{"type":"Inclusion","text":"Room Only"}]},"roomIndex":9,"hotelCode":null,"children":null,"roomTypeCode":null,"roomName":"Twin room","rateType":"Non Refundable","reprice":"R"},{"contractType":"O","isCache":false,"reprice":"R","children":null,"sMeal":"Room_Only","mealDescription":"Room Only","shortCode":"ArabianOryx","group":null,"roomIdentifier":2,"hotelCode":null,"roomName":"Twin room","mealCode":"RO","minStay":null,"inclusions":[{"text":"Room Only","type":"Inclusion"}],"remarks":{"remark":[{"type":"Inclusion","text":"Room Only"}]},"roomCombinationId":1831,"roomTypeCode":null,"rateType":"Non Refundable","supplierGroupCode":183,"policies":null,"adult":2,"groupCode":175,"guests":null,"rateKey":"1082519!TB!12!TB!84df4dff-fc73-11f0-822a-b62521cc9858!TB!N!TB!AFF!|2O","bedTypes":null,"marriageIdentifier":1831,"isCancelationPolicyAvailble":true,"extraBedCount":null,"price":{"isPackage":false,"supplierGross":373.01,"supplierNet":373.01,"supplierCommission":0,"gross":373.01,"taxType":null,"extraBedPrice":0,"isExclusiveRate":false,"promotions":null,"net":373.01,"isDynamic":false,"priceBreakdownRules":null,"supplierExtraBedPrice":0,"tax":0,"commission":0,"discount":null,"supplierCurrency":"AED","supplierTax":0,"currency":null,"isB2C":false},"roomIndex":29,"spHotelCode":null,"meal":"Room Only","status":"Available","isPriceBreakupAvailable":true},{"hotelCode":null,"roomCombinationId":1832,"mealCode":"RO","mealDescription":"Room Only","bedTypes":null,"adult":2,"roomTypeCode":null,"roomName":"Standard Room With Two Single-Size Beds Non Refundable","supplierGroupCode":183,"reprice":"R","isCancelationPolicyAvailble":true,"extraBedCount":null,"remarks":{"remark":[{"type":"Inclusion","text":"Room Only"}]},"inclusions":[{"type":"Inclusion","text":"Room Only"}],"roomIndex":10,"rateType":"Non Refundable","groupCode":175,"isCache":false,"policies":null,"price":{"priceBreakdownRules":null,"supplierGross":380.31,"supplierCommission":0,"net":380.31,"taxType":null,"isExclusiveRate":false,"supplierTax":0,"isB2C":false,"isDynamic":false,"promotions":null,"supplierNet":380.31,"discount":null,"extraBedPrice":0,"isPackage":false,"supplierCurrency":"AED","supplierExtraBedPrice":0,"currency":null,"gross":380.31,"tax":0,"commission":0},"children":null,"marriageIdentifier":1832,"contractType":"O","status":"Available","roomIdentifier":1,"meal":"Room Only","shortCode":"ArabianOryx","group":null,"spHotelCode":null,"rateKey":"1082519!TB!16!TB!84df4dff-fc73-11f0-822a-b62521cc9858!TB!N!TB!AFF!|1O","guests":null,"sMeal":"Room_Only","minStay":null,"isPriceBreakupAvailable":true},{"marriageIdentifier":1833,"mealCode":"RO","roomIndex":11,"roomTypeCode":null,"meal":"Room Only","groupCode":175,"isCache":false,"isPriceBreakupAvailable":true,"roomIdentifier":1,"guests":null,"shortCode":"ArabianOryx","policies":null,"remarks":{"remark":[{"type":"Inclusion","text":"Room Only"}]},"adult":2,"mealDescription":"Room Only","rateKey":"1082519!TB!6!TB!84df4dff-fc73-11f0-822a-b62521cc9858!TB!N!TB!AFF!|1O","contractType":"O","bedTypes":null,"children":null,"sMeal":"Room_Only","status":"Available","minStay":null,"reprice":"R","isCancelationPolicyAvailble":true,"price":{"supplierTax":0,"supplierNet":380.31,"net":380.31,"taxType":null,"extraBedPrice":0,"priceBreakdownRules":null,"supplierGross":380.31,"supplierCommission":0,"tax":0,"commission":0,"supplierCurrency":"AED","supplierExtraBedPrice":0,"currency":null,"gross":380.31,"isB2C":false,"isPackage":false,"isDynamic":false,"isExclusiveRate":false,"discount":null,"promotions":null},"hotelCode":null,"roomCombinationId":1833,"roomName":"Standard Room With One Double-Size Bed Non Refundable","rateType":"Non Refundable","inclusions":[{"type":"Inclusion","text":"Room Only"}],"spHotelCode":null,"supplierGroupCode":183,"group":null,"extraBedCount":null},{"minStay":null,"policies":null,"price":{"commission":0,"isDynamic":false,"isExclusiveRate":false,"supplierCurrency":"AED","supplierNet":380.31,"gross":380.31,"net":380.31,"discount":null,"supplierTax":0,"supplierCommission":0,"supplierExtraBedPrice":0,"isB2C":false,"isPackage":false,"priceBreakdownRules":null,"supplierGross":380.31,"currency":null,"extraBedPrice":0,"promotions":null,"tax":0,"taxType":null},"spHotelCode":null,"roomCombinationId":1832,"supplierGroupCode":183,"shortCode":"ArabianOryx","extraBedCount":null,"bedTypes":null,"sMeal":"Room_Only","rateType":"Non Refundable","reprice":"R","isPriceBreakupAvailable":true,"roomName":"Standard Room With Two Single-Size Beds Non Refundable","mealDescription":"Room Only","group":null,"inclusions":[{"type":"Inclusion","text":"Room Only"}],"remarks":{"remark":[{"text":"Room Only","type":"Inclusion"}]},"mealCode":"RO","groupCode":175,"roomIdentifier":2,"adult":2,"marriageIdentifier":1832,"rateKey":"1082519!TB!16!TB!84df4dff-fc73-11f0-822a-b62521cc9858!TB!N!TB!AFF!|2O","status":"Available","isCancelationPolicyAvailble":true,"guests":null,"meal":"Room Only","contractType":"O","isCache":false,"roomIndex":30,"children":null,"hotelCode":null,"roomTypeCode":null},{"roomCombinationId":1833,"marriageIdentifier":1833,"status":"Available","reprice":"R","isPriceBreakupAvailable":true,"price":{"currency":null,"net":380.31,"discount":null,"extraBedPrice":0,"commission":0,"isB2C":false,"supplierCurrency":"AED","supplierTax":0,"supplierNet":380.31,"supplierCommission":0,"taxType":null,"isPackage":false,"promotions":null,"supplierGross":380.31,"supplierExtraBedPrice":0,"gross":380.31,"tax":0,"isDynamic":false,"isExclusiveRate":false,"priceBreakdownRules":null},"guests":null,"hotelCode":null,"isCancelationPolicyAvailble":true,"adult":2,"roomName":"Standard Room With One Double-Size Bed Non Refundable","policies":null,"remarks":{"remark":[{"type":"Inclusion","text":"Room Only"}]},"children":null,"mealCode":"RO","isCache":false,"extraBedCount":null,"rateType":"Non Refundable","rateKey":"1082519!TB!6!TB!84df4dff-fc73-11f0-822a-b62521cc9858!TB!N!TB!AFF!|2O","shortCode":"ArabianOryx","mealDescription":"Room Only","supplierGroupCode":183,"inclusions":[{"type":"Inclusion","text":"Room Only"}],"roomIndex":31,"roomIdentifier":2,"roomTypeCode":null,"meal":"Room Only","sMeal":"Room_Only","minStay":null,"group":null,"bedTypes":null,"spHotelCode":null,"contractType":"O","groupCode":175},{"hotelCode":null,"rateKey":"1082519!TB!9!TB!84df4dff-fc73-11f0-822a-b62521cc9858!TB!N!TB!AFF!|1O","minStay":null,"bedTypes":null,"mealCode":"RO","mealDescription":"Room Only","contractType":"O","status":"Available","isCancelationPolicyAvailble":true,"roomIdentifier":1,"roomCombinationId":1834,"marriageIdentifier":1834,"shortCode":"ArabianOryx","group":null,"roomTypeCode":null,"sMeal":"Room_Only","isCache":false,"roomIndex":12,"meal":"Room Only","rateType":"Non Refundable","groupCode":175,"policies":null,"spHotelCode":null,"isPriceBreakupAvailable":true,"remarks":{"remark":[{"type":"Inclusion","text":"Room Only"}]},"adult":2,"children":null,"inclusions":[{"type":"Inclusion","text":"Room Only"}],"price":{"currency":null,"gross":381.83,"discount":null,"promotions":null,"supplierGross":381.83,"supplierTax":0,"taxType":null,"commission":0,"isDynamic":false,"supplierCurrency":"AED","supplierNet":381.83,"supplierCommission":0,"supplierExtraBedPrice":0,"tax":0,"extraBedPrice":0,"isB2C":false,"priceBreakdownRules":null,"net":381.83,"isPackage":false,"isExclusiveRate":false},"guests":null,"roomName":"Double room","supplierGroupCode":183,"reprice":"R","extraBedCount":null},{"children":null,"spHotelCode":null,"roomName":"Double room","remarks":{"remark":[{"type":"Inclusion","text":"Room Only"}]},"groupCode":175,"bedTypes":null,"roomIndex":32,"status":"Available","shortCode":"ArabianOryx","policies":null,"price":{"supplierNet":381.83,"currency":null,"tax":0,"commission":0,"discount":null,"isPackage":false,"supplierGross":381.83,"gross":381.83,"supplierTax":0,"supplierCommission":0,"taxType":null,"extraBedPrice":0,"isB2C":false,"isDynamic":false,"isExclusiveRate":false,"promotions":null,"supplierCurrency":"AED","supplierExtraBedPrice":0,"net":381.83,"priceBreakdownRules":null},"mealCode":"RO","supplierGroupCode":183,"minStay":null,"isCancelationPolicyAvailble":true,"inclusions":[{"type":"Inclusion","text":"Room Only"}],"adult":2,"guests":null,"marriageIdentifier":1834,"roomTypeCode":null,"sMeal":"Room_Only","rateType":"Non Refundable","reprice":"R","mealDescription":"Room Only","contractType":"O","group":null,"hotelCode":null,"meal":"Room Only","isCache":false,"isPriceBreakupAvailable":true,"roomIdentifier":2,"roomCombinationId":1834,"rateKey":"1082519!TB!9!TB!84df4dff-fc73-11f0-822a-b62521cc9858!TB!N!TB!AFF!|2O","extraBedCount":null},{"rateKey":"35619644_796265_28_9999-19861389O","roomIndex":1,"marriageIdentifier":1361,"shortCode":"ArabianOryx","children":null,"roomName":"Standard Room with Two Single-Size Beds","contractType":"O","isCache":false,"minStay":"","reprice":"R","supplierGroupCode":136,"inclusions":null,"spHotelCode":null,"sMeal":"Room Only","rateType":"Non Refundable","status":"Available","isCancelationPolicyAvailble":true,"extraBedCount":null,"roomIdentifier":1,"meal":"Room Only","mealDescription":"Room Only","policies":null,"adult":2,"guests":null,"hotelCode":null,"roomCombinationId":1361,"roomTypeCode":null,"mealCode":"RO","isPriceBreakupAvailable":true,"price":{"taxType":"Tax","isB2C":false,"isDynamic":true,"promotions":null,"priceBreakdownRules":null,"supplierGross":359.02,"supplierNet":439.8,"supplierExtraBedPrice":0,"gross":359.02,"commission":0,"discount":null,"isExclusiveRate":false,"supplierTax":80.79,"tax":80.79,"currency":null,"net":439.8,"extraBedPrice":0,"isPackage":false,"supplierCurrency":"AED","supplierCommission":0},"groupCode":175,"group":null,"bedTypes":null,"remarks":null},{"meal":"Room Only","isCancelationPolicyAvailble":true,"adult":2,"spHotelCode":null,"sMeal":"Room Only","rateKey":"35619645_796265_28_9999-19861389O","minStay":"","guests":null,"status":"Available","reprice":"R","isPriceBreakupAvailable":true,"roomIdentifier":1,"roomCombinationId":1362,"roomName":"Standard Room with One Double-Size Bed","contractType":"O","bedTypes":null,"hotelCode":null,"marriageIdentifier":1362,"roomTypeCode":null,"mealDescription":"Room Only","rateType":"Non Refundable","supplierGroupCode":136,"isCache":false,"group":null,"mealCode":"RO","shortCode":"ArabianOryx","extraBedCount":null,"inclusions":null,"remarks":null,"roomIndex":2,"groupCode":175,"policies":null,"price":{"supplierNet":439.8,"commission":0,"supplierGross":359.02,"discount":null,"isB2C":false,"supplierCommission":0,"supplierExtraBedPrice":0,"currency":null,"gross":359.02,"extraBedPrice":0,"isExclusiveRate":false,"promotions":null,"supplierTax":80.79,"net":439.8,"tax":80.79,"taxType":"Tax","isPackage":false,"isDynamic":true,"priceBreakdownRules":null,"supplierCurrency":"AED"},"children":null},{"remarks":null,"adult":2,"spHotelCode":null,"roomCombinationId":1361,"inclusions":null,"contractType":"O","status":"Available","policies":null,"children":null,"guests":null,"hotelCode":null,"roomTypeCode":null,"roomName":"Standard Room with Two Single-Size Beds","mealDescription":"Room Only","group":null,"extraBedCount":null,"roomIdentifier":2,"mealCode":"RO","rateType":"Non Refundable","supplierGroupCode":136,"isPriceBreakupAvailable":true,"isCancelationPolicyAvailble":true,"reprice":"R","price":{"supplierCurrency":"AED","supplierGross":359.02,"supplierExtraBedPrice":0,"taxType":"Tax","discount":null,"extraBedPrice":0,"isB2C":false,"isPackage":false,"supplierTax":80.79,"supplierCommission":0,"net":439.8,"tax":80.79,"commission":0,"priceBreakdownRules":null,"supplierNet":439.8,"isDynamic":true,"isExclusiveRate":false,"currency":null,"gross":359.02,"promotions":null},"marriageIdentifier":1361,"meal":"Room Only","sMeal":"Room Only","rateKey":"35619644_796265_28_9999-19861389O","groupCode":175,"isCache":false,"bedTypes":null,"roomIndex":5,"shortCode":"ArabianOryx","minStay":""},{"isCancelationPolicyAvailble":true,"bedTypes":null,"adult":2,"roomCombinationId":1362,"roomTypeCode":null,"roomName":"Standard Room with One Double-Size Bed","children":null,"shortCode":"ArabianOryx","roomIndex":6,"group":null,"inclusions":null,"policies":null,"price":{"discount":null,"isPackage":false,"isDynamic":true,"supplierGross":359.02,"supplierExtraBedPrice":0,"taxType":"Tax","extraBedPrice":0,"isB2C":false,"supplierCurrency":"AED","tax":80.79,"commission":0,"supplierTax":80.79,"supplierNet":439.8,"isExclusiveRate":false,"promotions":null,"priceBreakdownRules":null,"supplierCommission":0,"currency":null,"gross":359.02,"net":439.8},"hotelCode":null,"spHotelCode":null,"mealCode":"RO","meal":"Room Only","sMeal":"Room Only","supplierGroupCode":136,"extraBedCount":null,"remarks":null,"guests":null,"marriageIdentifier":1362,"mealDescription":"Room Only","rateType":"Non Refundable","groupCode":175,"minStay":"","reprice":"R","isPriceBreakupAvailable":true,"rateKey":"35619645_796265_28_9999-19861389O","contractType":"O","roomIdentifier":2,"status":"Available","isCache":false},{"guests":null,"roomTypeCode":null,"isCancelationPolicyAvailble":true,"extraBedCount":null,"price":{"gross":357.27,"taxType":null,"supplierTax":101.45,"supplierExtraBedPrice":0,"isPackage":false,"priceBreakdownRules":null,"supplierGross":357.27,"supplierCommission":0,"currency":null,"net":458.71,"commission":0,"discount":null,"extraBedPrice":0,"isDynamic":false,"supplierCurrency":"AED","supplierNet":458.71,"tax":101.45,"isB2C":false,"isExclusiveRate":false,"promotions":null},"adult":2,"spHotelCode":null,"supplierGroupCode":183,"roomIdentifier":1,"roomName":"Standard Room with One Double-Size Bed","mealCode":"RO","bedTypes":null,"inclusions":[{"type":"Inclusion","text":"Room Only"}],"rateKey":"1082519!TB!7!TB!84df4dff-fc73-11f0-822a-b62521cc9858!TB!N!TB!AFF!|1O","isCache":false,"group":null,"policies":null,"reprice":"R","isPriceBreakupAvailable":true,"remarks":{"remark":[{"type":"Inclusion","text":"Room Only"}]},"roomIndex":13,"children":null,"hotelCode":null,"marriageIdentifier":1835,"mealDescription":"Room Only","rateType":"Non Refundable","contractType":"O","status":"Available","roomCombinationId":1835,"meal":"Room Only","sMeal":"Room_Only","groupCode":175,"minStay":null,"shortCode":"ArabianOryx"},{"remarks":{"remark":[{"type":"Inclusion","text":"Room Only"}]},"roomCombinationId":1836,"roomName":"Standard Room with Two Single-Size Beds","guests":null,"sMeal":"Room_Only","shortCode":"ArabianOryx","reprice":"R","hotelCode":null,"roomTypeCode":null,"mealCode":"RO","supplierGroupCode":183,"minStay":null,"adult":2,"spHotelCode":null,"isCache":false,"mealDescription":"Room Only","rateType":"Non Refundable","contractType":"O","price":{"supplierGross":357.27,"supplierNet":458.71,"net":458.71,"tax":101.45,"taxType":null,"isExclusiveRate":false,"gross":357.27,"extraBedPrice":0,"isB2C":false,"priceBreakdownRules":null,"supplierTax":101.45,"supplierExtraBedPrice":0,"commission":0,"discount":null,"supplierCurrency":"AED","supplierCommission":0,"currency":null,"isPackage":false,"isDynamic":false,"promotions":null},"children":null,"meal":"Room Only","rateKey":"1082519!TB!18!TB!84df4dff-fc73-11f0-822a-b62521cc9858!TB!N!TB!AFF!|1O","isCancelationPolicyAvailble":true,"policies":null,"roomIdentifier":1,"status":"Available","isPriceBreakupAvailable":true,"extraBedCount":null,"roomIndex":14,"marriageIdentifier":1836,"groupCode":175,"group":null,"bedTypes":null,"inclusions":[{"type":"Inclusion","text":"Room Only"}]},{"roomCombinationId":1835,"mealCode":"RO","mealDescription":"Room Only","supplierGroupCode":183,"guests":null,"hotelCode":null,"meal":"Room Only","shortCode":"ArabianOryx","reprice":"R","roomIdentifier":2,"roomName":"Standard Room with One Double-Size Bed","contractType":"O","isPriceBreakupAvailable":true,"bedTypes":null,"spHotelCode":null,"group":null,"roomTypeCode":null,"rateKey":"1082519!TB!7!TB!84df4dff-fc73-11f0-822a-b62521cc9858!TB!N!TB!AFF!|2O","minStay":null,"children":null,"marriageIdentifier":1835,"sMeal":"Room_Only","status":"Available","groupCode":175,"extraBedCount":null,"inclusions":[{"type":"Inclusion","text":"Room Only"}],"policies":null,"rateType":"Non Refundable","isCache":false,"remarks":{"remark":[{"type":"Inclusion","text":"Room Only"}]},"roomIndex":33,"adult":2,"isCancelationPolicyAvailble":true,"price":{"tax":101.45,"taxType":null,"isPackage":false,"promotions":null,"supplierNet":458.71,"supplierCommission":0,"discount":null,"priceBreakdownRules":null,"supplierCurrency":"AED","supplierGross":357.27,"supplierTax":101.45,"supplierExtraBedPrice":0,"net":458.71,"isB2C":false,"isDynamic":false,"commission":0,"extraBedPrice":0,"isExclusiveRate":false,"currency":null,"gross":357.27}},{"mealDescription":"Room Only","rateType":"Non Refundable","groupCode":175,"supplierGroupCode":183,"group":null,"reprice":"R","inclusions":[{"type":"Inclusion","text":"Room Only"}],"children":null,"spHotelCode":null,"roomCombinationId":1836,"shortCode":"ArabianOryx","isPriceBreakupAvailable":true,"remarks":{"remark":[{"type":"Inclusion","text":"Room Only"}]},"roomIndex":34,"adult":2,"meal":"Room Only","minStay":null,"extraBedCount":null,"roomIdentifier":2,"hotelCode":null,"guests":null,"roomTypeCode":null,"rateKey":"1082519!TB!18!TB!84df4dff-fc73-11f0-822a-b62521cc9858!TB!N!TB!AFF!|2O","contractType":"O","status":"Available","isCancelationPolicyAvailble":true,"bedTypes":null,"policies":null,"roomName":"Standard Room with Two Single-Size Beds","mealCode":"RO","sMeal":"Room_Only","isCache":false,"price":{"net":458.71,"discount":null,"isB2C":false,"supplierTax":101.45,"supplierExtraBedPrice":0,"currency":null,"taxType":null,"commission":0,"isExclusiveRate":false,"promotions":null,"supplierGross":357.27,"supplierNet":458.71,"extraBedPrice":0,"priceBreakdownRules":null,"supplierCurrency":"AED","supplierCommission":0,"gross":357.27,"tax":101.45,"isPackage":false,"isDynamic":false},"marriageIdentifier":1836},{"roomIndex":49,"spHotelCode":null,"minStay":null,"remarks":null,"roomCombinationId":1356141,"sMeal":"Free WiFi","contractType":"O","roomIdentifier":1,"adult":2,"marriageIdentifier":1356141,"roomTypeCode":null,"mealDescription":"Room Only","children":null,"shortCode":"ArabianOryx","group":null,"bedTypes":{"bedType":"FullBed"},"inclusions":null,"price":{"supplierExtraBedPrice":0,"currency":null,"gross":368.9,"net":460.7,"isExclusiveRate":false,"supplierTax":91.8,"supplierNet":460.7,"tax":91.8,"supplierCommission":0,"taxType":"tax_and_service_fee","commission":0,"isB2C":false,"isDynamic":false,"promotions":[],"priceBreakdownRules":null,"supplierCurrency":"AED","supplierGross":368.9,"discount":null,"extraBedPrice":0,"isPackage":true},"hotelCode":null,"roomName":"Standard Double Room, 1 Double Bed","meal":"Room Only","rateType":"Non-Refundable","reprice":"R","guests":null,"rateKey":"401445014PO","groupCode":175,"supplierGroupCode":135,"mealCode":"RO","status":"Available","isCache":null,"isPriceBreakupAvailable":true,"isCancelationPolicyAvailble":true,"extraBedCount":null,"policies":null},{"hotelCode":null,"rateType":"Non-Refundable","contractType":"O","isPriceBreakupAvailable":true,"price":{"promotions":[],"supplierCommission":0,"gross":368.9,"extraBedPrice":0,"isDynamic":false,"isExclusiveRate":false,"priceBreakdownRules":null,"supplierGross":368.9,"supplierNet":460.7,"net":460.7,"isB2C":false,"supplierTax":91.8,"supplierExtraBedPrice":0,"taxType":"tax_and_service_fee","discount":null,"supplierCurrency":"AED","currency":null,"tax":91.8,"commission":0,"isPackage":true},"spHotelCode":null,"meal":"Room Only","sMeal":"Free WiFi","rateKey":"401445014PO","groupCode":175,"extraBedCount":null,"roomIndex":50,"adult":2,"guests":null,"roomTypeCode":null,"mealDescription":"Room Only","status":"Available","bedTypes":{"bedType":"FullBed"},"remarks":null,"children":null,"roomCombinationId":1356141,"supplierGroupCode":135,"shortCode":"ArabianOryx","inclusions":null,"marriageIdentifier":1356141,"roomName":"Standard Double Room, 1 Double Bed","isCache":null,"mealCode":"RO","reprice":"R","policies":null,"minStay":null,"group":null,"isCancelationPolicyAvailble":true,"roomIdentifier":2},{"adult":2,"mealCode":"RO","supplierGroupCode":135,"isPriceBreakupAvailable":true,"policies":null,"roomName":"Standard Room, 2 Twin Beds","sMeal":"Free WiFi","mealDescription":"Room Only","group":null,"extraBedCount":null,"roomTypeCode":null,"meal":"Room Only","shortCode":"ArabianOryx","inclusions":null,"hotelCode":null,"remarks":null,"roomIndex":55,"roomIdentifier":1,"guests":null,"rateKey":"201193315PO","status":"Available","isCache":null,"reprice":"R","bedTypes":{"bedType":"TwinBed"},"rateType":"Non-Refundable","contractType":"O","marriageIdentifier":1356144,"groupCode":175,"children":null,"spHotelCode":null,"roomCombinationId":1356144,"minStay":null,"isCancelationPolicyAvailble":true,"price":{"supplierTax":91.8,"net":467.3,"tax":91.8,"taxType":"tax_and_service_fee","discount":null,"isB2C":false,"isPackage":true,"supplierGross":375.5,"gross":375.5,"extraBedPrice":0,"currency":null,"isExclusiveRate":false,"promotions":[],"priceBreakdownRules":null,"supplierCurrency":"AED","supplierNet":467.3,"supplierCommission":0,"supplierExtraBedPrice":0,"commission":0,"isDynamic":false}},{"inclusions":null,"roomIndex":56,"children":null,"marriageIdentifier":1356144,"mealDescription":"Room Only","contractType":"O","isCache":null,"bedTypes":{"bedType":"TwinBed"},"price":{"supplierGross":375.5,"currency":null,"net":467.3,"isPackage":true,"isDynamic":false,"isExclusiveRate":false,"promotions":[],"supplierTax":91.8,"supplierNet":467.3,"supplierCommission":0,"taxType":"tax_and_service_fee","commission":0,"isB2C":false,"supplierExtraBedPrice":0,"gross":375.5,"tax":91.8,"discount":null,"supplierCurrency":"AED","extraBedPrice":0,"priceBreakdownRules":null},"mealCode":"RO","spHotelCode":null,"roomCombinationId":1356144,"isCancelationPolicyAvailble":true,"minStay":null,"policies":null,"roomIdentifier":2,"roomTypeCode":null,"sMeal":"Free WiFi","reprice":"R","remarks":null,"hotelCode":null,"meal":"Room Only","rateKey":"201193315PO","status":"Available","groupCode":175,"group":null,"isPriceBreakupAvailable":true,"roomName":"Standard Room, 2 Twin Beds","supplierGroupCode":135,"shortCode":"ArabianOryx","adult":2,"guests":null,"rateType":"Non-Refundable","extraBedCount":null},{"children":null,"hotelCode":null,"mealDescription":"Room Only","rateType":"Non-Refundable","reprice":"R","extraBedCount":null,"rateKey":"401445014SO","supplierGroupCode":135,"minStay":null,"inclusions":null,"status":"Available","isCache":null,"isPriceBreakupAvailable":true,"guests":null,"sMeal":"Free WiFi","contractType":"O","policies":null,"roomIdentifier":1,"spHotelCode":null,"roomCombinationId":1356145,"roomTypeCode":null,"group":null,"isCancelationPolicyAvailble":true,"roomIndex":57,"mealCode":"RO","groupCode":175,"shortCode":"ArabianOryx","adult":2,"marriageIdentifier":1356145,"roomName":"Standard Double Room, 1 Double Bed","meal":"Room Only","bedTypes":{"bedType":"FullBed"},"price":{"priceBreakdownRules":null,"supplierTax":91.8,"supplierNet":467.62,"currency":null,"net":467.62,"isPackage":false,"supplierGross":375.82,"gross":375.82,"commission":0,"discount":null,"isB2C":false,"isExclusiveRate":false,"supplierExtraBedPrice":0,"tax":91.8,"taxType":"tax_and_service_fee","promotions":[],"supplierCurrency":"AED","supplierCommission":0,"extraBedPrice":0,"isDynamic":false},"remarks":null},{"children":null,"contractType":"O","isCache":null,"isCancelationPolicyAvailble":true,"spHotelCode":null,"roomCombinationId":1356145,"sMeal":"Free WiFi","reprice":"R","bedTypes":{"bedType":"FullBed"},"status":"Available","minStay":null,"isPriceBreakupAvailable":true,"hotelCode":null,"roomTypeCode":null,"supplierGroupCode":135,"shortCode":"ArabianOryx","group":null,"policies":null,"roomIndex":58,"groupCode":175,"roomIdentifier":2,"guests":null,"roomName":"Standard Double Room, 1 Double Bed","mealCode":"RO","mealDescription":"Room Only","rateType":"Non-Refundable","rateKey":"401445014SO","inclusions":null,"adult":2,"extraBedCount":null,"price":{"supplierTax":91.8,"net":467.62,"commission":0,"isB2C":false,"supplierExtraBedPrice":0,"gross":375.82,"tax":91.8,"discount":null,"isDynamic":false,"priceBreakdownRules":null,"supplierCurrency":"AED","supplierGross":375.82,"supplierNet":467.62,"currency":null,"extraBedPrice":0,"isPackage":false,"isExclusiveRate":false,"supplierCommission":0,"taxType":"tax_and_service_fee","promotions":[]},"remarks":null,"marriageIdentifier":1356145,"meal":"Room Only"},{"policies":null,"price":{"isDynamic":false,"isExclusiveRate":false,"priceBreakdownRules":null,"supplierCurrency":"AED","supplierTax":86.26,"commission":0,"isPackage":false,"extraBedPrice":0,"isB2C":false,"promotions":null,"supplierGross":383.36,"supplierNet":469.61,"supplierCommission":0,"supplierExtraBedPrice":0,"currency":null,"tax":86.26,"discount":null,"gross":383.36,"net":469.61,"taxType":null},"roomIndex":15,"guests":null,"rateType":"Non Refundable","inclusions":[{"type":"Inclusion","text":"COFFEE & TEA,FREE WIFI,DRINKING WATER"}],"roomIdentifier":1,"marriageIdentifier":1837,"sMeal":"Room_Only","mealDescription":"Room Only","status":"Available","children":null,"hotelCode":null,"roomCombinationId":1837,"mealCode":"RO","meal":"Room Only","groupCode":175,"bedTypes":null,"roomName":"Standard Twin Room","shortCode":"ArabianOryx","spHotelCode":null,"roomTypeCode":null,"supplierGroupCode":183,"group":null,"isCancelationPolicyAvailble":true,"remarks":{"remark":[{"type":"Inclusion","text":"COFFEE & TEA,FREE WIFI,DRINKING WATER"},{"type":"Supplements","text":"Type : AtProperty, Description : Tourism Dirham Fee, Price : 10.88, Currency : USD."}]},"contractType":"O","isCache":false,"adult":2,"rateKey":"1082519!TB!17!TB!84df4dff-fc73-11f0-822a-b62521cc9858!TB!N!TB!AFF!|1O","minStay":null,"reprice":"R","isPriceBreakupAvailable":true,"extraBedCount":null},{"inclusions":[{"type":"Inclusion","text":"COFFEE & TEA,FREE WIFI,DRINKING WATER"}],"roomIdentifier":2,"hotelCode":null,"isCache":false,"roomIndex":35,"children":null,"mealCode":"RO","sMeal":"Room_Only","rateKey":"1082519!TB!17!TB!84df4dff-fc73-11f0-822a-b62521cc9858!TB!N!TB!AFF!|2O","shortCode":"ArabianOryx","isPriceBreakupAvailable":true,"isCancelationPolicyAvailble":true,"spHotelCode":null,"roomCombinationId":1837,"marriageIdentifier":1837,"roomName":"Standard Twin Room","reprice":"R","extraBedCount":null,"price":{"extraBedPrice":0,"isPackage":false,"isExclusiveRate":false,"supplierTax":86.26,"supplierNet":469.61,"net":469.61,"commission":0,"discount":null,"isDynamic":false,"priceBreakdownRules":null,"supplierGross":383.36,"supplierExtraBedPrice":0,"gross":383.36,"tax":86.26,"currency":null,"taxType":null,"isB2C":false,"promotions":null,"supplierCurrency":"AED","supplierCommission":0},"minStay":null,"group":null,"guests":null,"adult":2,"rateType":"Non Refundable","contractType":"O","status":"Available","remarks":{"remark":[{"text":"COFFEE & TEA,FREE WIFI,DRINKING WATER","type":"Inclusion"},{"text":"Type : AtProperty, Description : Tourism Dirham Fee, Price : 10.88, Currency : USD.","type":"Supplements"}]},"mealDescription":"Room Only","groupCode":175,"supplierGroupCode":183,"bedTypes":null,"policies":null,"roomTypeCode":null,"meal":"Room Only"},{"spHotelCode":null,"marriageIdentifier":1356148,"mealDescription":"Room Only","rateType":"Non-Refundable","reprice":"R","price":{"net":472.28,"tax":91.8,"taxType":"tax_and_service_fee","discount":null,"isPackage":false,"isExclusiveRate":false,"currency":null,"gross":380.48,"supplierGross":380.48,"commission":0,"isB2C":false,"supplierCurrency":"AED","supplierNet":472.28,"supplierExtraBedPrice":0,"extraBedPrice":0,"isDynamic":false,"promotions":[],"priceBreakdownRules":null,"supplierTax":91.8,"supplierCommission":0},"hotelCode":null,"roomIndex":63,"children":null,"guests":null,"sMeal":"Free WiFi","minStay":null,"group":null,"bedTypes":{"bedType":"TwinBed"},"groupCode":175,"extraBedCount":null,"policies":null,"roomIdentifier":1,"adult":2,"roomCombinationId":1356148,"roomName":"Standard Room, 2 Twin Beds","mealCode":"RO","status":"Available","roomTypeCode":null,"meal":"Room Only","rateKey":"201193315SO","shortCode":"ArabianOryx","isCancelationPolicyAvailble":true,"contractType":"O","supplierGroupCode":135,"isCache":null,"inclusions":null,"remarks":null,"isPriceBreakupAvailable":true},{"adult":2,"roomIdentifier":2,"spHotelCode":null,"marriageIdentifier":1356148,"meal":"Room Only","inclusions":null,"children":null,"remarks":null,"hotelCode":null,"roomCombinationId":1356148,"roomTypeCode":null,"supplierGroupCode":135,"group":null,"reprice":"R","isPriceBreakupAvailable":true,"extraBedCount":null,"roomName":"Standard Room, 2 Twin Beds","isCancelationPolicyAvailble":true,"policies":null,"roomIndex":64,"guests":null,"mealCode":"RO","mealDescription":"Room Only","rateType":"Non-Refundable","contractType":"O","groupCode":175,"shortCode":"ArabianOryx","sMeal":"Free WiFi","status":"Available","minStay":null,"bedTypes":{"bedType":"TwinBed"},"rateKey":"201193315SO","isCache":null,"price":{"supplierNet":472.28,"supplierCommission":0,"supplierExtraBedPrice":0,"gross":380.48,"taxType":"tax_and_service_fee","isExclusiveRate":false,"promotions":[],"supplierGross":380.48,"net":472.28,"discount":null,"priceBreakdownRules":null,"supplierCurrency":"AED","supplierTax":91.8,"currency":null,"commission":0,"isB2C":false,"tax":91.8,"extraBedPrice":0,"isPackage":false,"isDynamic":false}},{"roomCombinationId":1838,"group":null,"adult":2,"hotelCode":null,"marriageIdentifier":1838,"meal":"Room Only","groupCode":175,"supplierGroupCode":183,"isCancelationPolicyAvailble":true,"spHotelCode":null,"mealDescription":"Room Only","shortCode":"ArabianOryx","price":{"supplierTax":0,"tax":0,"taxType":null,"isDynamic":false,"promotions":null,"supplierNet":503.75,"net":503.75,"extraBedPrice":0,"isExclusiveRate":false,"supplierCurrency":"AED","supplierGross":503.75,"supplierExtraBedPrice":0,"currency":null,"discount":null,"isB2C":false,"isPackage":false,"supplierCommission":0,"gross":503.75,"commission":0,"priceBreakdownRules":null},"roomIdentifier":1,"isCache":false,"minStay":null,"reprice":"R","bedTypes":null,"roomTypeCode":null,"roomName":"Standard Double Room, 1 Double Bed","sMeal":"Room_Only","extraBedCount":null,"inclusions":[{"type":"Inclusion","text":"Room Only"}],"roomIndex":16,"rateType":"Non Refundable","isPriceBreakupAvailable":true,"policies":null,"children":null,"status":"Available","remarks":{"remark":[{"type":"Inclusion","text":"Room Only"},{"type":"Supplements","text":"Type : AtProperty, Description : mandatory_tax, Price : 5.46, Currency : USD."}]},"guests":null,"mealCode":"RO","rateKey":"1082519!TB!10!TB!84df4dff-fc73-11f0-822a-b62521cc9858!TB!N!TB!AFF!|1O","contractType":"O"},{"roomIdentifier":2,"roomTypeCode":null,"supplierGroupCode":183,"isCache":false,"isPriceBreakupAvailable":true,"marriageIdentifier":1838,"sMeal":"Room_Only","rateType":"Non Refundable","rateKey":"1082519!TB!10!TB!84df4dff-fc73-11f0-822a-b62521cc9858!TB!N!TB!AFF!|2O","shortCode":"ArabianOryx","group":null,"bedTypes":null,"roomIndex":36,"adult":2,"guests":null,"hotelCode":null,"extraBedCount":null,"children":null,"meal":"Room Only","status":"Available","groupCode":175,"reprice":"R","price":{"commission":0,"isB2C":false,"isDynamic":false,"supplierTax":0,"supplierCommission":0,"net":503.75,"isExclusiveRate":false,"promotions":null,"gross":503.75,"discount":null,"extraBedPrice":0,"priceBreakdownRules":null,"supplierCurrency":"AED","supplierGross":503.75,"isPackage":false,"supplierNet":503.75,"supplierExtraBedPrice":0,"currency":null,"tax":0,"taxType":null},"spHotelCode":null,"roomName":"Standard Double Room, 1 Double Bed","mealDescription":"Room Only","inclusions":[{"text":"Room Only","type":"Inclusion"}],"policies":null,"remarks":{"remark":[{"type":"Inclusion","text":"Room Only"},{"type":"Supplements","text":"Type : AtProperty, Description : mandatory_tax, Price : 5.46, Currency : USD."}]},"roomCombinationId":1838,"minStay":null,"mealCode":"RO","contractType":"O","isCancelationPolicyAvailble":true},{"roomIdentifier":1,"status":"Available","isPriceBreakupAvailable":true,"remarks":{"remark":[{"type":"Inclusion","text":"Room Only"},{"type":"Supplements","text":"Type : AtProperty, Description : mandatory_tax, Price : 20.0, Currency : AED."}]},"guests":null,"rateKey":"1082519!TB!13!TB!84df4dff-fc73-11f0-822a-b62521cc9858!TB!N!TB!AFF!|1O","shortCode":"ArabianOryx","roomIndex":17,"hotelCode":null,"meal":"Room Only","group":null,"adult":2,"mealDescription":"Room Only","rateType":"Non Refundable","reprice":"R","children":null,"roomCombinationId":1839,"supplierGroupCode":183,"bedTypes":null,"marriageIdentifier":1839,"roomTypeCode":null,"roomName":"Standard Double Room, 1 Double Bed,NonSmoking","sMeal":"Room_Only","groupCode":175,"isCancelationPolicyAvailble":true,"extraBedCount":null,"price":{"supplierTax":101.15,"commission":0,"extraBedPrice":0,"isPackage":false,"isDynamic":false,"supplierExtraBedPrice":0,"currency":null,"discount":null,"isB2C":false,"supplierCurrency":"AED","supplierGross":402.76,"supplierCommission":0,"gross":402.76,"net":503.9,"tax":101.15,"taxType":null,"priceBreakdownRules":null,"supplierNet":503.9,"isExclusiveRate":false,"promotions":null},"spHotelCode":null,"contractType":"O","isCache":false,"minStay":null,"policies":null,"mealCode":"RO","inclusions":[{"type":"Inclusion","text":"Room Only"}]},{"groupCode":175,"group":null,"isCancelationPolicyAvailble":true,"policies":null,"price":{"supplierCurrency":"AED","supplierGross":402.76,"isDynamic":false,"promotions":null,"gross":402.76,"net":503.9,"taxType":null,"extraBedPrice":0,"isExclusiveRate":false,"priceBreakdownRules":null,"supplierNet":503.9,"currency":null,"commission":0,"discount":null,"isB2C":false,"isPackage":false,"supplierTax":101.15,"supplierCommission":0,"supplierExtraBedPrice":0,"tax":101.15},"contractType":"O","bedTypes":null,"inclusions":[{"type":"Inclusion","text":"Room Only"}],"roomIdentifier":2,"adult":2,"hotelCode":null,"spHotelCode":null,"roomCombinationId":1839,"rateType":"Non Refundable","shortCode":"ArabianOryx","isCache":false,"children":null,"guests":null,"mealCode":"RO","sMeal":"Room_Only","supplierGroupCode":183,"minStay":null,"extraBedCount":null,"roomIndex":37,"roomTypeCode":null,"mealDescription":"Room Only","reprice":"R","remarks":{"remark":[{"type":"Inclusion","text":"Room Only"},{"type":"Supplements","text":"Type : AtProperty, Description : mandatory_tax, Price : 20.0, Currency : AED."}]},"marriageIdentifier":1839,"meal":"Room Only","status":"Available","isPriceBreakupAvailable":true,"rateKey":"1082519!TB!13!TB!84df4dff-fc73-11f0-822a-b62521cc9858!TB!N!TB!AFF!|2O","roomName":"Standard Double Room, 1 Double Bed,NonSmoking"},{"guests":null,"status":"Available","isPriceBreakupAvailable":true,"extraBedCount":null,"roomIndex":18,"roomIdentifier":1,"roomCombinationId":18310,"mealCode":"RO","shortCode":"ArabianOryx","minStay":null,"bedTypes":null,"remarks":{"remark":[{"text":"Room Only","type":"Inclusion"},{"type":"Supplements","text":"Type : AtProperty, Description : Tourism Fee, Price : 10.88, Currency : USD.\nType : Included, Description : VAT, Price : 11.13, Currency : USD.\nType : Included, Description : Municipality Fee, Price : 14.14, Currency : USD.\nType : Included, Description : Service Charge, Price : 20.2, Currency : USD."}]},"inclusions":[{"type":"Inclusion","text":"Room Only"}],"hotelCode":null,"roomTypeCode":null,"roomName":"Standard Room 1 Double Bed Non Smoking","sMeal":"Room_Only","isCache":false,"policies":null,"marriageIdentifier":18310,"mealDescription":"Room Only","rateType":"Non Refundable","supplierGroupCode":183,"group":null,"reprice":"R","isCancelationPolicyAvailble":true,"price":{"supplierGross":319.33,"supplierCommission":0,"currency":null,"commission":0,"extraBedPrice":0,"promotions":null,"priceBreakdownRules":null,"supplierCurrency":"AED","supplierNet":504.94,"net":504.94,"taxType":null,"isB2C":false,"supplierTax":185.62,"supplierExtraBedPrice":0,"gross":319.33,"tax":185.62,"discount":null,"isDynamic":false,"isPackage":false,"isExclusiveRate":false},"spHotelCode":null,"adult":2,"rateKey":"1082519!TB!5!TB!84df4dff-fc73-11f0-822a-b62521cc9858!TB!N!TB!AFF!|1O","contractType":"O","groupCode":175,"children":null,"meal":"Room Only"},{"adult":2,"children":null,"shortCode":"ArabianOryx","group":null,"isCache":false,"spHotelCode":null,"contractType":"O","groupCode":175,"reprice":"R","inclusions":[{"type":"Inclusion","text":"Room Only"}],"roomIndex":38,"roomCombinationId":18310,"sMeal":"Room_Only","rateType":"Non Refundable","status":"Available","supplierGroupCode":183,"hotelCode":null,"roomName":"Standard Room 1 Double Bed Non Smoking","bedTypes":null,"marriageIdentifier":18310,"roomTypeCode":null,"meal":"Room Only","rateKey":"1082519!TB!5!TB!84df4dff-fc73-11f0-822a-b62521cc9858!TB!N!TB!AFF!|2O","isCancelationPolicyAvailble":true,"remarks":{"remark":[{"type":"Inclusion","text":"Room Only"},{"type":"Supplements","text":"Type : AtProperty, Description : Tourism Fee, Price : 10.88, Currency : USD.\nType : Included, Description : VAT, Price : 11.13, Currency : USD.\nType : Included, Description : Municipality Fee, Price : 14.14, Currency : USD.\nType : Included, Description : Service Charge, Price : 20.2, Currency : USD."}]},"roomIdentifier":2,"mealDescription":"Room Only","minStay":null,"extraBedCount":null,"policies":null,"price":{"net":504.94,"extraBedPrice":0,"currency":null,"tax":185.62,"taxType":null,"isB2C":false,"isExclusiveRate":false,"supplierCurrency":"AED","gross":319.33,"isPackage":false,"isDynamic":false,"priceBreakdownRules":null,"supplierGross":319.33,"supplierTax":185.62,"supplierExtraBedPrice":0,"commission":0,"discount":null,"promotions":null,"supplierNet":504.94,"supplierCommission":0},"guests":null,"mealCode":"RO","isPriceBreakupAvailable":true},{"roomIdentifier":1,"minStay":null,"bedTypes":null,"price":{"taxType":null,"promotions":null,"priceBreakdownRules":null,"supplierCurrency":"AED","supplierTax":101.22,"supplierNet":511.46,"supplierExtraBedPrice":0,"currency":null,"gross":410.24,"discount":null,"isExclusiveRate":false,"supplierCommission":0,"net":511.46,"commission":0,"isB2C":false,"isPackage":false,"isDynamic":false,"supplierGross":410.24,"tax":101.22,"extraBedPrice":0},"remarks":{"remark":[{"type":"Inclusion","text":"Room Only"},{"type":"Supplements","text":"Type : AtProperty, Description : mandatory_tax, Price : 20.0, Currency : AED."}]},"roomIndex":19,"adult":2,"isCancelationPolicyAvailble":true,"policies":null,"children":null,"mealCode":"RO","sMeal":"Room_Only","marriageIdentifier":18311,"roomTypeCode":null,"meal":"Room Only","rateKey":"1082519!TB!4!TB!84df4dff-fc73-11f0-822a-b62521cc9858!TB!N!TB!AFF!|1O","status":"Available","shortCode":"ArabianOryx","isPriceBreakupAvailable":true,"groupCode":175,"extraBedCount":null,"hotelCode":null,"contractType":"O","isCache":false,"spHotelCode":null,"roomName":"Standard Room, 2 Twin Beds,NonSmoking","rateType":"Non Refundable","supplierGroupCode":183,"group":null,"reprice":"R","guests":null,"roomCombinationId":18311,"mealDescription":"Room Only","inclusions":[{"type":"Inclusion","text":"Room Only"}]},{"roomIndex":39,"roomIdentifier":2,"shortCode":"ArabianOryx","minStay":null,"isPriceBreakupAvailable":true,"guests":null,"status":"Available","extraBedCount":null,"hotelCode":null,"rateType":"Non Refundable","contractType":"O","reprice":"R","roomName":"Standard Room, 2 Twin Beds,NonSmoking","sMeal":"Room_Only","inclusions":[{"type":"Inclusion","text":"Room Only"}],"adult":2,"children":null,"roomCombinationId":18311,"mealDescription":"Room Only","groupCode":175,"spHotelCode":null,"marriageIdentifier":18311,"mealCode":"RO","rateKey":"1082519!TB!4!TB!84df4dff-fc73-11f0-822a-b62521cc9858!TB!N!TB!AFF!|2O","group":null,"isCancelationPolicyAvailble":true,"bedTypes":null,"remarks":{"remark":[{"type":"Inclusion","text":"Room Only"},{"type":"Supplements","text":"Type : AtProperty, Description : mandatory_tax, Price : 20.0, Currency : AED."}]},"meal":"Room Only","supplierGroupCode":183,"isCache":false,"policies":null,"price":{"currency":null,"tax":101.22,"taxType":null,"extraBedPrice":0,"priceBreakdownRules":null,"supplierCurrency":"AED","commission":0,"isB2C":false,"supplierGross":410.24,"supplierNet":511.46,"discount":null,"promotions":null,"supplierTax":101.22,"supplierExtraBedPrice":0,"gross":410.24,"net":511.46,"isPackage":false,"isDynamic":false,"isExclusiveRate":false,"supplierCommission":0},"roomTypeCode":null},{"group":null,"reprice":"R","inclusions":[{"type":"Inclusion","text":"Breakfast"}],"roomIndex":20,"meal":"Bed and Breakfast","marriageIdentifier":18312,"roomName":"Double room","rateKey":"1082519!TB!20!TB!84df4dff-fc73-11f0-822a-b62521cc9858!TB!N!TB!AFF!|1O","supplierGroupCode":183,"isPriceBreakupAvailable":true,"remarks":{"remark":[{"type":"Inclusion","text":"Breakfast"}]},"roomTypeCode":null,"mealDescription":"Break Fast included","roomIdentifier":1,"status":"Available","shortCode":"ArabianOryx","isCancelationPolicyAvailble":true,"hotelCode":null,"mealCode":"BB","sMeal":"BreakFast","groupCode":175,"price":{"supplierGross":601.1,"supplierExtraBedPrice":0,"taxType":null,"isB2C":false,"isPackage":false,"isDynamic":false,"promotions":null,"priceBreakdownRules":null,"gross":601.1,"tax":0,"discount":null,"supplierCurrency":"AED","supplierNet":601.1,"currency":null,"net":601.1,"commission":0,"isExclusiveRate":false,"supplierTax":0,"supplierCommission":0,"extraBedPrice":0},"children":null,"spHotelCode":null,"rateType":"Non Refundable","minStay":null,"policies":null,"contractType":"O","extraBedCount":null,"bedTypes":null,"adult":2,"guests":null,"roomCombinationId":18312,"isCache":false},{"groupCode":175,"isCache":false,"price":{"currency":null,"gross":601.1,"extraBedPrice":0,"supplierGross":601.1,"supplierCommission":0,"tax":0,"taxType":null,"discount":null,"isDynamic":false,"isExclusiveRate":false,"promotions":null,"supplierTax":0,"supplierNet":601.1,"isB2C":false,"priceBreakdownRules":null,"supplierCurrency":"AED","supplierExtraBedPrice":0,"net":601.1,"commission":0,"isPackage":false},"remarks":{"remark":[{"type":"Inclusion","text":"Breakfast"}]},"roomCombinationId":18313,"status":"Available","shortCode":"ArabianOryx","inclusions":[{"type":"Inclusion","text":"Breakfast"}],"mealCode":"BB","hotelCode":null,"roomName":"Twin room","isPriceBreakupAvailable":true,"meal":"Bed and Breakfast","mealDescription":"Break Fast included","supplierGroupCode":183,"extraBedCount":null,"policies":null,"roomIdentifier":1,"roomTypeCode":null,"rateType":"Non Refundable","contractType":"O","reprice":"R","isCancelationPolicyAvailble":true,"adult":2,"bedTypes":null,"children":null,"spHotelCode":null,"marriageIdentifier":18313,"minStay":null,"group":null,"roomIndex":21,"guests":null,"sMeal":"BreakFast","rateKey":"1082519!TB!11!TB!84df4dff-fc73-11f0-822a-b62521cc9858!TB!N!TB!AFF!|1O"},{"adult":2,"marriageIdentifier":18312,"contractType":"O","policies":null,"roomIdentifier":2,"spHotelCode":null,"status":"Available","isCancelationPolicyAvailble":true,"inclusions":[{"type":"Inclusion","text":"Breakfast"}],"roomIndex":40,"roomCombinationId":18312,"roomTypeCode":null,"sMeal":"BreakFast","groupCode":175,"reprice":"R","bedTypes":null,"roomName":"Double room","mealCode":"BB","mealDescription":"Break Fast included","group":null,"extraBedCount":null,"hotelCode":null,"supplierGroupCode":183,"isCache":false,"minStay":null,"price":{"supplierExtraBedPrice":0,"tax":0,"isPackage":false,"isExclusiveRate":false,"priceBreakdownRules":null,"supplierNet":601.1,"supplierCommission":0,"currency":null,"net":601.1,"commission":0,"extraBedPrice":0,"supplierTax":0,"discount":null,"isB2C":false,"isDynamic":false,"promotions":null,"supplierCurrency":"AED","supplierGross":601.1,"gross":601.1,"taxType":null},"isPriceBreakupAvailable":true,"remarks":{"remark":[{"type":"Inclusion","text":"Breakfast"}]},"children":null,"rateType":"Non Refundable","shortCode":"ArabianOryx","guests":null,"meal":"Bed and Breakfast","rateKey":"1082519!TB!20!TB!84df4dff-fc73-11f0-822a-b62521cc9858!TB!N!TB!AFF!|2O"},{"marriageIdentifier":18313,"roomTypeCode":null,"contractType":"O","sMeal":"BreakFast","rateKey":"1082519!TB!11!TB!84df4dff-fc73-11f0-822a-b62521cc9858!TB!N!TB!AFF!|2O","policies":null,"remarks":{"remark":[{"text":"Breakfast","type":"Inclusion"}]},"roomIdentifier":2,"supplierGroupCode":183,"group":null,"isPriceBreakupAvailable":true,"bedTypes":null,"guests":null,"spHotelCode":null,"roomName":"Twin room","meal":"Bed and Breakfast","groupCode":175,"shortCode":"ArabianOryx","isCache":false,"rateType":"Non Refundable","minStay":null,"extraBedCount":null,"adult":2,"reprice":"R","inclusions":[{"type":"Inclusion","text":"Breakfast"}],"roomIndex":41,"hotelCode":null,"roomCombinationId":18313,"mealCode":"BB","mealDescription":"Break Fast included","status":"Available","isCancelationPolicyAvailble":true,"price":{"supplierCommission":0,"gross":601.1,"discount":null,"isDynamic":false,"isExclusiveRate":false,"supplierCurrency":"AED","supplierGross":601.1,"supplierNet":601.1,"currency":null,"tax":0,"extraBedPrice":0,"isPackage":false,"priceBreakdownRules":null,"supplierExtraBedPrice":0,"net":601.1,"commission":0,"promotions":null,"taxType":null,"isB2C":false,"supplierTax":0},"children":null},{"roomCombinationId":18314,"roomName":"Standard Room With One Double-Size Bed Non Refundable","mealCode":"BB","rateType":"Non Refundable","contractType":"O","roomTypeCode":null,"groupCode":175,"supplierGroupCode":183,"isCache":false,"group":null,"reprice":"R","isPriceBreakupAvailable":true,"roomIndex":22,"roomIdentifier":1,"spHotelCode":null,"marriageIdentifier":18314,"rateKey":"1082519!TB!1!TB!84df4dff-fc73-11f0-822a-b62521cc9858!TB!N!TB!AFF!|1O","status":"Available","minStay":null,"isCancelationPolicyAvailble":true,"adult":2,"meal":"Bed and Breakfast","bedTypes":null,"policies":null,"price":{"supplierCurrency":"AED","supplierNet":613.12,"supplierExtraBedPrice":0,"currency":null,"tax":0,"commission":0,"extraBedPrice":0,"isExclusiveRate":false,"supplierGross":613.12,"supplierCommission":0,"discount":null,"isB2C":false,"isDynamic":false,"priceBreakdownRules":null,"net":613.12,"taxType":null,"isPackage":false,"promotions":null,"supplierTax":0,"gross":613.12},"children":null,"mealDescription":"Break Fast included","extraBedCount":null,"inclusions":[{"type":"Inclusion","text":"Breakfast"}],"guests":null,"sMeal":"BreakFast","remarks":{"remark":[{"type":"Inclusion","text":"Breakfast"}]},"hotelCode":null,"shortCode":"ArabianOryx"},{"adult":2,"guests":null,"marriageIdentifier":18315,"isPriceBreakupAvailable":true,"isCancelationPolicyAvailble":true,"roomIndex":23,"contractType":"O","groupCode":175,"supplierGroupCode":183,"meal":"Bed and Breakfast","sMeal":"BreakFast","mealDescription":"Break Fast included","isCache":false,"rateKey":"1082519!TB!8!TB!84df4dff-fc73-11f0-822a-b62521cc9858!TB!N!TB!AFF!|1O","status":"Available","policies":null,"remarks":{"remark":[{"text":"Breakfast","type":"Inclusion"}]},"roomIdentifier":1,"hotelCode":null,"roomCombinationId":18315,"extraBedCount":null,"price":{"isExclusiveRate":false,"promotions":null,"supplierCurrency":"AED","supplierNet":613.12,"tax":0,"commission":0,"priceBreakdownRules":null,"supplierGross":613.12,"supplierCommission":0,"supplierTax":0,"currency":null,"net":613.12,"taxType":null,"isDynamic":false,"supplierExtraBedPrice":0,"gross":613.12,"discount":null,"extraBedPrice":0,"isB2C":false,"isPackage":false},"children":null,"shortCode":"ArabianOryx","group":null,"inclusions":[{"type":"Inclusion","text":"Breakfast"}],"roomName":"Standard Room With Two Single-Size Beds Non Refundable","mealCode":"BB","rateType":"Non Refundable","reprice":"R","bedTypes":null,"spHotelCode":null,"roomTypeCode":null,"minStay":null},{"roomTypeCode":null,"sMeal":"BreakFast","supplierGroupCode":183,"roomIndex":42,"children":null,"contractType":"O","extraBedCount":null,"remarks":{"remark":[{"type":"Inclusion","text":"Breakfast"}]},"roomIdentifier":2,"meal":"Bed and Breakfast","group":null,"guests":null,"mealDescription":"Break Fast included","groupCode":175,"reprice":"R","policies":null,"roomCombinationId":18314,"rateType":"Non Refundable","isCancelationPolicyAvailble":true,"spHotelCode":null,"marriageIdentifier":18314,"shortCode":"ArabianOryx","bedTypes":null,"inclusions":[{"type":"Inclusion","text":"Breakfast"}],"price":{"supplierCurrency":"AED","gross":613.12,"net":613.12,"taxType":null,"discount":null,"priceBreakdownRules":null,"supplierCommission":0,"currency":null,"extraBedPrice":0,"isB2C":false,"isDynamic":false,"isExclusiveRate":false,"supplierTax":0,"supplierNet":613.12,"promotions":null,"supplierGross":613.12,"supplierExtraBedPrice":0,"tax":0,"commission":0,"isPackage":false},"adult":2,"hotelCode":null,"roomName":"Standard Room With One Double-Size Bed Non Refundable","isCache":false,"minStay":null,"mealCode":"BB","rateKey":"1082519!TB!1!TB!84df4dff-fc73-11f0-822a-b62521cc9858!TB!N!TB!AFF!|2O","status":"Available","isPriceBreakupAvailable":true},{"adult":2,"mealCode":"BB","meal":"Bed and Breakfast","mealDescription":"Break Fast included","rateType":"Non Refundable","isCancelationPolicyAvailble":true,"bedTypes":null,"remarks":{"remark":[{"type":"Inclusion","text":"Breakfast"}]},"marriageIdentifier":18315,"status":"Available","shortCode":"ArabianOryx","policies":null,"roomCombinationId":18315,"group":null,"isPriceBreakupAvailable":true,"roomName":"Standard Room With Two Single-Size Beds Non Refundable","sMeal":"BreakFast","groupCode":175,"inclusions":[{"type":"Inclusion","text":"Breakfast"}],"rateKey":"1082519!TB!8!TB!84df4dff-fc73-11f0-822a-b62521cc9858!TB!N!TB!AFF!|2O","extraBedCount":null,"roomIndex":43,"roomTypeCode":null,"supplierGroupCode":183,"price":{"gross":613.12,"tax":0,"isB2C":false,"promotions":null,"supplierNet":613.12,"supplierExtraBedPrice":0,"taxType":null,"isDynamic":false,"priceBreakdownRules":null,"supplierCommission":0,"currency":null,"commission":0,"isPackage":false,"supplierCurrency":"AED","supplierGross":613.12,"supplierTax":0,"net":613.12,"discount":null,"extraBedPrice":0,"isExclusiveRate":false},"roomIdentifier":2,"guests":null,"contractType":"O","isCache":false,"minStay":null,"children":null,"hotelCode":null,"spHotelCode":null,"reprice":"R"},{"adult":2,"hotelCode":null,"roomTypeCode":null,"mealDescription":"Break Fast included","contractType":"O","shortCode":"ArabianOryx","roomCombinationId":1363,"groupCode":175,"isCancelationPolicyAvailble":true,"inclusions":null,"marriageIdentifier":1363,"meal":"Bed and Breakfast","sMeal":"Breakfast","rateKey":"35619644_796271_7_9999-19861389O","supplierGroupCode":136,"policies":null,"roomName":"Standard Room with Two Single-Size Beds","mealCode":"BB","status":"Available","isCache":false,"minStay":"","price":{"supplierTax":130.26,"supplierCommission":0,"isB2C":false,"isPackage":false,"priceBreakdownRules":null,"supplierNet":709.05,"currency":null,"tax":130.26,"commission":0,"discount":null,"isDynamic":true,"isExclusiveRate":false,"supplierGross":578.8,"supplierExtraBedPrice":0,"gross":578.8,"net":709.05,"promotions":null,"taxType":"Tax","extraBedPrice":0,"supplierCurrency":"AED"},"roomIdentifier":1,"spHotelCode":null,"roomIndex":3,"group":null,"reprice":"R","bedTypes":null,"children":null,"guests":null,"rateType":"Non Refundable","isPriceBreakupAvailable":true,"extraBedCount":null,"remarks":null},{"roomIdentifier":1,"minStay":"","price":{"supplierCurrency":"AED","supplierGross":578.8,"supplierExtraBedPrice":0,"net":709.05,"isB2C":false,"promotions":null,"supplierTax":130.26,"commission":0,"extraBedPrice":0,"isPackage":false,"isDynamic":true,"supplierNet":709.05,"supplierCommission":0,"tax":130.26,"currency":null,"gross":578.8,"taxType":"Tax","discount":null,"isExclusiveRate":false,"priceBreakdownRules":null},"children":null,"spHotelCode":null,"roomCombinationId":1364,"roomName":"Standard Room with One Double-Size Bed","meal":"Bed and Breakfast","isCache":false,"guests":null,"hotelCode":null,"mealDescription":"Break Fast included","status":"Available","supplierGroupCode":136,"group":null,"bedTypes":null,"marriageIdentifier":1364,"rateType":"Non Refundable","rateKey":"35619645_796271_7_9999-19861389O","contractType":"O","groupCode":175,"inclusions":null,"mealCode":"BB","shortCode":"ArabianOryx","extraBedCount":null,"remarks":null,"roomIndex":4,"roomTypeCode":null,"reprice":"R","isPriceBreakupAvailable":true,"policies":null,"adult":2,"sMeal":"Breakfast","isCancelationPolicyAvailble":true},{"roomCombinationId":1363,"roomName":"Standard Room with Two Single-Size Beds","isCancelationPolicyAvailble":true,"bedTypes":null,"roomIndex":7,"rateType":"Non Refundable","isCache":false,"isPriceBreakupAvailable":true,"inclusions":null,"adult":2,"spHotelCode":null,"meal":"Bed and Breakfast","mealDescription":"Break Fast included","shortCode":"ArabianOryx","mealCode":"BB","status":"Available","group":null,"price":{"isB2C":false,"isDynamic":true,"isExclusiveRate":false,"supplierGross":578.8,"currency":null,"gross":578.8,"extraBedPrice":0,"isPackage":false,"supplierCurrency":"AED","supplierExtraBedPrice":0,"tax":130.26,"priceBreakdownRules":null,"supplierNet":709.05,"net":709.05,"discount":null,"promotions":null,"supplierTax":130.26,"supplierCommission":0,"taxType":"Tax","commission":0},"children":null,"marriageIdentifier":1363,"reprice":"R","remarks":null,"hotelCode":null,"sMeal":"Breakfast","contractType":"O","groupCode":175,"roomTypeCode":null,"rateKey":"35619644_796271_7_9999-19861389O","supplierGroupCode":136,"minStay":"","extraBedCount":null,"policies":null,"roomIdentifier":2,"guests":null},{"mealCode":"BB","group":null,"price":{"isDynamic":true,"promotions":null,"currency":null,"priceBreakdownRules":null,"supplierTax":130.26,"net":709.05,"tax":130.26,"commission":0,"supplierCurrency":"AED","supplierGross":578.8,"supplierNet":709.05,"gross":578.8,"taxType":"Tax","discount":null,"isPackage":false,"isExclusiveRate":false,"supplierCommission":0,"supplierExtraBedPrice":0,"extraBedPrice":0,"isB2C":false},"roomIndex":8,"sMeal":"Breakfast","shortCode":"ArabianOryx","isPriceBreakupAvailable":true,"roomIdentifier":2,"adult":2,"children":null,"roomName":"Standard Room with One Double-Size Bed","meal":"Bed and Breakfast","extraBedCount":null,"hotelCode":null,"roomCombinationId":1364,"supplierGroupCode":136,"isCache":false,"minStay":"","isCancelationPolicyAvailble":true,"guests":null,"marriageIdentifier":1364,"rateType":"Non Refundable","remarks":null,"bedTypes":null,"roomTypeCode":null,"mealDescription":"Break Fast included","rateKey":"35619645_796271_7_9999-19861389O","contractType":"O","status":"Available","groupCode":175,"inclusions":null,"policies":null,"spHotelCode":null,"reprice":"R"},{"roomCombinationId":18316,"meal":"Bed and Breakfast","status":"Available","supplierGroupCode":183,"extraBedCount":null,"roomName":"Standard Room with Two Single-Size Beds","mealCode":"BB","sMeal":"BreakFast","contractType":"O","isPriceBreakupAvailable":true,"inclusions":[{"type":"Inclusion","text":"Breakfast"}],"remarks":{"remark":[{"text":"Breakfast","type":"Inclusion"}]},"hotelCode":null,"reprice":"R","rateType":"Non Refundable","groupCode":175,"group":null,"adult":2,"children":null,"spHotelCode":null,"roomTypeCode":null,"rateKey":"1082519!TB!2!TB!84df4dff-fc73-11f0-822a-b62521cc9858!TB!N!TB!AFF!|1O","shortCode":"ArabianOryx","minStay":null,"isCancelationPolicyAvailble":true,"roomIndex":24,"guests":null,"marriageIdentifier":18316,"mealDescription":"Break Fast included","isCache":false,"bedTypes":null,"policies":null,"price":{"supplierNet":726.66,"supplierExtraBedPrice":0,"extraBedPrice":0,"isExclusiveRate":false,"priceBreakdownRules":null,"supplierCurrency":"AED","supplierTax":150.66,"supplierCommission":0,"gross":576.01,"taxType":null,"commission":0,"promotions":null,"supplierGross":576.01,"currency":null,"tax":150.66,"discount":null,"isB2C":false,"net":726.66,"isPackage":false,"isDynamic":false},"roomIdentifier":1},{"adult":2,"extraBedCount":null,"roomIdentifier":1,"price":{"promotions":null,"currency":null,"net":726.66,"commission":0,"discount":null,"isB2C":false,"isDynamic":false,"isExclusiveRate":false,"supplierCurrency":"AED","tax":150.66,"taxType":null,"extraBedPrice":0,"priceBreakdownRules":null,"supplierTax":150.66,"supplierNet":726.66,"supplierCommission":0,"gross":576.01,"isPackage":false,"supplierGross":576.01,"supplierExtraBedPrice":0},"hotelCode":null,"spHotelCode":null,"policies":null,"roomIndex":25,"children":null,"meal":"Bed and Breakfast","rateType":"Non Refundable","groupCode":175,"supplierGroupCode":183,"bedTypes":null,"roomCombinationId":18317,"roomName":"Standard Room with One Double-Size Bed","mealDescription":"Break Fast included","status":"Available","reprice":"R","isCancelationPolicyAvailble":true,"guests":null,"mealCode":"BB","shortCode":"ArabianOryx","isCache":false,"remarks":{"remark":[{"text":"Breakfast","type":"Inclusion"}]},"sMeal":"BreakFast","contractType":"O","minStay":null,"inclusions":[{"type":"Inclusion","text":"Breakfast"}],"marriageIdentifier":18317,"roomTypeCode":null,"rateKey":"1082519!TB!14!TB!84df4dff-fc73-11f0-822a-b62521cc9858!TB!N!TB!AFF!|1O","group":null,"isPriceBreakupAvailable":true},{"meal":"Bed and Breakfast","rateType":"Non Refundable","reprice":"R","isCancelationPolicyAvailble":true,"policies":null,"marriageIdentifier":18316,"rateKey":"1082519!TB!2!TB!84df4dff-fc73-11f0-822a-b62521cc9858!TB!N!TB!AFF!|2O","remarks":{"remark":[{"type":"Inclusion","text":"Breakfast"}]},"mealDescription":"Break Fast included","status":"Available","minStay":null,"roomIdentifier":2,"spHotelCode":null,"adult":2,"children":null,"roomCombinationId":18316,"roomName":"Standard Room with Two Single-Size Beds","contractType":"O","bedTypes":null,"groupCode":175,"sMeal":"BreakFast","group":null,"extraBedCount":null,"inclusions":[{"type":"Inclusion","text":"Breakfast"}],"guests":null,"roomTypeCode":null,"supplierGroupCode":183,"shortCode":"ArabianOryx","isCache":false,"isPriceBreakupAvailable":true,"price":{"taxType":null,"isDynamic":false,"priceBreakdownRules":null,"supplierTax":150.66,"supplierNet":726.66,"tax":150.66,"discount":null,"extraBedPrice":0,"supplierCommission":0,"currency":null,"net":726.66,"commission":0,"isB2C":false,"isPackage":false,"isExclusiveRate":false,"supplierGross":576.01,"supplierExtraBedPrice":0,"promotions":null,"supplierCurrency":"AED","gross":576.01},"roomIndex":44,"hotelCode":null,"mealCode":"BB"},{"spHotelCode":null,"marriageIdentifier":18317,"sMeal":"BreakFast","rateKey":"1082519!TB!14!TB!84df4dff-fc73-11f0-822a-b62521cc9858!TB!N!TB!AFF!|2O","contractType":"O","status":"Available","bedTypes":null,"policies":null,"roomIdentifier":2,"mealDescription":"Break Fast included","isCache":false,"inclusions":[{"type":"Inclusion","text":"Breakfast"}],"remarks":{"remark":[{"text":"Breakfast","type":"Inclusion"}]},"mealCode":"BB","minStay":null,"roomIndex":45,"children":null,"groupCode":175,"roomName":"Standard Room with One Double-Size Bed","hotelCode":null,"roomCombinationId":18317,"meal":"Bed and Breakfast","supplierGroupCode":183,"group":null,"isPriceBreakupAvailable":true,"extraBedCount":null,"adult":2,"guests":null,"rateType":"Non Refundable","isCancelationPolicyAvailble":true,"price":{"supplierNet":726.66,"supplierCommission":0,"net":726.66,"isB2C":false,"isPackage":false,"supplierCurrency":"AED","supplierGross":576.01,"currency":null,"gross":576.01,"tax":150.66,"supplierTax":150.66,"discount":null,"isExclusiveRate":false,"promotions":null,"priceBreakdownRules":null,"supplierExtraBedPrice":0,"taxType":null,"commission":0,"extraBedPrice":0,"isDynamic":false},"roomTypeCode":null,"shortCode":"ArabianOryx","reprice":"R"},{"bedTypes":{"bedType":"FullBed"},"policies":null,"price":{"supplierCurrency":"AED","supplierNet":749.88,"commission":0,"isPackage":true,"supplierGross":601.89,"supplierExtraBedPrice":0,"net":749.88,"extraBedPrice":0,"priceBreakdownRules":null,"supplierTax":148,"currency":null,"taxType":"tax_and_service_fee","discount":null,"isB2C":false,"isExclusiveRate":false,"supplierCommission":0,"gross":601.89,"tax":148,"isDynamic":false,"promotions":[]},"roomIndex":51,"status":"Available","groupCode":175,"reprice":"R","inclusions":null,"adult":2,"roomName":"Standard Double Room, 1 Double Bed","isCancelationPolicyAvailble":true,"guests":null,"mealCode":"BB","sMeal":"Free breakfast,Free WiFi","shortCode":"ArabianOryx","extraBedCount":null,"roomTypeCode":null,"rateType":"Non-Refundable","children":null,"rateKey":"401445025PO","supplierGroupCode":135,"isCache":null,"isPriceBreakupAvailable":true,"spHotelCode":null,"marriageIdentifier":1356142,"mealDescription":"Break Fast included","contractType":"O","minStay":null,"group":null,"remarks":null,"roomIdentifier":1,"hotelCode":null,"roomCombinationId":1356142,"meal":"Bed and Breakfast"},{"hotelCode":null,"rateType":"Non-Refundable","status":"Available","policies":null,"adult":2,"marriageIdentifier":1356142,"mealCode":"BB","mealDescription":"Break Fast included","isCache":null,"isCancelationPolicyAvailble":true,"spHotelCode":null,"groupCode":175,"shortCode":"ArabianOryx","children":null,"roomTypeCode":null,"roomName":"Standard Double Room, 1 Double Bed","group":null,"bedTypes":{"bedType":"FullBed"},"guests":null,"meal":"Bed and Breakfast","supplierGroupCode":135,"minStay":null,"remarks":null,"rateKey":"401445025PO","reprice":"R","roomIndex":52,"roomCombinationId":1356142,"contractType":"O","isPriceBreakupAvailable":true,"roomIdentifier":2,"sMeal":"Free breakfast,Free WiFi","extraBedCount":null,"inclusions":null,"price":{"supplierNet":749.88,"currency":null,"commission":0,"extraBedPrice":0,"isB2C":false,"supplierGross":601.89,"supplierTax":148,"supplierExtraBedPrice":0,"gross":601.89,"net":749.88,"taxType":"tax_and_service_fee","isPackage":true,"isDynamic":false,"supplierCurrency":"AED","tax":148,"discount":null,"isExclusiveRate":false,"promotions":[],"priceBreakdownRules":null,"supplierCommission":0}},{"contractType":"O","isCancelationPolicyAvailble":true,"hotelCode":null,"sMeal":"Free breakfast,Free WiFi","rateType":"Non-Refundable","bedTypes":{"bedType":"TwinBed"},"price":{"tax":148,"extraBedPrice":0,"isDynamic":false,"promotions":[],"priceBreakdownRules":null,"supplierExtraBedPrice":0,"net":749.88,"supplierCurrency":"AED","supplierGross":601.89,"supplierTax":148,"supplierNet":749.88,"gross":601.89,"taxType":"tax_and_service_fee","commission":0,"discount":null,"currency":null,"isB2C":false,"isPackage":true,"isExclusiveRate":false,"supplierCommission":0},"spHotelCode":null,"meal":"Bed and Breakfast","isCache":null,"minStay":null,"group":null,"remarks":null,"children":null,"roomCombinationId":1356143,"roomTypeCode":null,"status":"Available","supplierGroupCode":135,"roomIdentifier":1,"guests":null,"marriageIdentifier":1356143,"roomName":"Standard Room, 2 Twin Beds","rateKey":"401444945PO","isPriceBreakupAvailable":true,"mealCode":"BB","mealDescription":"Break Fast included","groupCode":175,"extraBedCount":null,"inclusions":null,"roomIndex":53,"shortCode":"ArabianOryx","reprice":"R","policies":null,"adult":2},{"spHotelCode":null,"roomCombinationId":1356143,"isCache":null,"policies":null,"roomIndex":54,"roomName":"Standard Room, 2 Twin Beds","bedTypes":{"bedType":"TwinBed"},"children":null,"supplierGroupCode":135,"isCancelationPolicyAvailble":true,"extraBedCount":null,"price":{"extraBedPrice":0,"isPackage":true,"discount":null,"isDynamic":false,"isExclusiveRate":false,"priceBreakdownRules":null,"supplierCurrency":"AED","supplierGross":601.89,"supplierNet":749.88,"net":749.88,"commission":0,"isB2C":false,"promotions":[],"supplierCommission":0,"supplierTax":148,"supplierExtraBedPrice":0,"currency":null,"gross":601.89,"tax":148,"taxType":"tax_and_service_fee"},"guests":null,"sMeal":"Free breakfast,Free WiFi","rateKey":"401444945PO","shortCode":"ArabianOryx","minStay":null,"remarks":null,"roomIdentifier":2,"marriageIdentifier":1356143,"roomTypeCode":null,"mealCode":"BB","hotelCode":null,"meal":"Bed and Breakfast","mealDescription":"Break Fast included","status":"Available","groupCode":175,"reprice":"R","inclusions":null,"adult":2,"rateType":"Non-Refundable","contractType":"O","group":null,"isPriceBreakupAvailable":true},{"roomIndex":59,"mealCode":"BB","children":null,"guests":null,"meal":"Bed and Breakfast","supplierGroupCode":135,"contractType":"O","group":null,"roomCombinationId":1356146,"marriageIdentifier":1356146,"roomName":"Standard Double Room, 1 Double Bed","sMeal":"Free breakfast,Free WiFi","mealDescription":"Break Fast included","groupCode":175,"minStay":null,"inclusions":null,"hotelCode":null,"rateType":"Non-Refundable","rateKey":"401445025SO","status":"Available","shortCode":"ArabianOryx","remarks":null,"roomTypeCode":null,"isPriceBreakupAvailable":true,"bedTypes":{"bedType":"FullBed"},"policies":null,"price":{"net":753.89,"commission":0,"priceBreakdownRules":null,"taxType":"tax_and_service_fee","isExclusiveRate":false,"gross":605.9,"extraBedPrice":0,"isB2C":false,"promotions":[],"supplierCommission":0,"currency":null,"tax":148,"discount":null,"isPackage":false,"isDynamic":false,"supplierCurrency":"AED","supplierGross":605.9,"supplierTax":148,"supplierNet":753.89,"supplierExtraBedPrice":0},"roomIdentifier":1,"adult":2,"spHotelCode":null,"reprice":"R","isCancelationPolicyAvailble":true,"extraBedCount":null,"isCache":null},{"roomName":"Standard Double Room, 1 Double Bed","meal":"Bed and Breakfast","contractType":"O","isCancelationPolicyAvailble":true,"policies":null,"groupCode":175,"adult":2,"minStay":null,"remarks":null,"roomIdentifier":2,"guests":null,"hotelCode":null,"status":"Available","spHotelCode":null,"marriageIdentifier":1356146,"reprice":"R","inclusions":null,"price":{"supplierExtraBedPrice":0,"promotions":[],"currency":null,"tax":148,"commission":0,"isB2C":false,"priceBreakdownRules":null,"supplierCurrency":"AED","supplierCommission":0,"taxType":"tax_and_service_fee","extraBedPrice":0,"isPackage":false,"supplierGross":605.9,"supplierTax":148,"supplierNet":753.89,"gross":605.9,"net":753.89,"discount":null,"isDynamic":false,"isExclusiveRate":false},"children":null,"mealCode":"BB","sMeal":"Free breakfast,Free WiFi","mealDescription":"Break Fast included","supplierGroupCode":135,"isCache":null,"extraBedCount":null,"roomIndex":60,"shortCode":"ArabianOryx","group":null,"bedTypes":{"bedType":"FullBed"},"roomTypeCode":null,"rateType":"Non-Refundable","rateKey":"401445025SO","isPriceBreakupAvailable":true,"roomCombinationId":1356146},{"adult":2,"roomCombinationId":1356147,"roomName":"Standard Room, 2 Twin Beds","supplierGroupCode":135,"policies":null,"price":{"gross":605.9,"isB2C":false,"supplierExtraBedPrice":0,"tax":148,"isExclusiveRate":false,"supplierGross":605.9,"supplierTax":148,"supplierNet":753.89,"supplierCommission":0,"currency":null,"net":753.89,"commission":0,"discount":null,"supplierCurrency":"AED","taxType":"tax_and_service_fee","extraBedPrice":0,"isPackage":false,"isDynamic":false,"promotions":[],"priceBreakdownRules":null},"shortCode":"ArabianOryx","isPriceBreakupAvailable":true,"roomTypeCode":null,"reprice":"R","remarks":null,"spHotelCode":null,"marriageIdentifier":1356147,"sMeal":"Free breakfast,Free WiFi","contractType":"O","bedTypes":{"bedType":"TwinBed"},"meal":"Bed and Breakfast","status":"Available","isCache":null,"group":null,"inclusions":null,"mealCode":"BB","rateType":"Non-Refundable","groupCode":175,"extraBedCount":null,"roomIndex":61,"mealDescription":"Break Fast included","rateKey":"401444945SO","minStay":null,"roomIdentifier":1,"children":null,"guests":null,"hotelCode":null,"isCancelationPolicyAvailble":true},{"rateType":"Non-Refundable","supplierGroupCode":135,"isCancelationPolicyAvailble":true,"inclusions":null,"price":{"isPackage":false,"supplierNet":753.89,"supplierCommission":0,"supplierExtraBedPrice":0,"net":753.89,"promotions":[],"currency":null,"tax":148,"discount":null,"extraBedPrice":0,"isDynamic":false,"priceBreakdownRules":null,"supplierCurrency":"AED","supplierGross":605.9,"gross":605.9,"taxType":"tax_and_service_fee","isExclusiveRate":false,"supplierTax":148,"commission":0,"isB2C":false},"roomTypeCode":null,"rateKey":"401444945SO","contractType":"O","adult":2,"mealDescription":"Break Fast included","status":"Available","bedTypes":{"bedType":"TwinBed"},"policies":null,"roomIndex":62,"extraBedCount":null,"children":null,"marriageIdentifier":1356147,"groupCode":175,"shortCode":"ArabianOryx","remarks":null,"roomIdentifier":2,"meal":"Bed and Breakfast","minStay":null,"guests":null,"spHotelCode":null,"mealCode":"BB","sMeal":"Free breakfast,Free WiFi","isCache":null,"group":null,"reprice":"R","isPriceBreakupAvailable":true,"hotelCode":null,"roomCombinationId":1356147,"roomName":"Standard Room, 2 Twin Beds"},{"spHotelCode":null,"meal":"Bed and Breakfast","sMeal":"BreakFast","mealCode":"BB","shortCode":"ArabianOryx","minStay":null,"extraBedCount":null,"remarks":{"remark":[{"type":"Inclusion","text":"BREAKFAST,COFFEE & TEA,FREE WIFI,DRINKING WATER"},{"text":"Type : AtProperty, Description : Tourism Dirham Fee, Price : 10.88, Currency : USD.","type":"Supplements"}]},"children":null,"marriageIdentifier":18318,"roomTypeCode":null,"guests":null,"isCache":false,"isCancelationPolicyAvailble":true,"policies":null,"roomCombinationId":18318,"roomName":"Standard Twin Room","rateType":"Non Refundable","rateKey":"1082519!TB!19!TB!84df4dff-fc73-11f0-822a-b62521cc9858!TB!N!TB!AFF!|1O","groupCode":175,"supplierGroupCode":183,"bedTypes":null,"roomIndex":26,"roomIdentifier":1,"mealDescription":"Break Fast included","contractType":"O","status":"Available","reprice":"R","inclusions":[{"type":"Inclusion","text":"BREAKFAST,COFFEE & TEA,FREE WIFI,DRINKING WATER"}],"adult":2,"hotelCode":null,"price":{"taxType":null,"extraBedPrice":0,"isB2C":false,"isPackage":false,"priceBreakdownRules":null,"supplierCurrency":"AED","supplierGross":634.19,"supplierCommission":0,"currency":null,"tax":142.69,"discount":null,"isExclusiveRate":false,"supplierTax":142.69,"supplierNet":776.88,"net":776.88,"commission":0,"promotions":null,"isDynamic":false,"supplierExtraBedPrice":0,"gross":634.19},"group":null,"isPriceBreakupAvailable":true},{"guests":null,"spHotelCode":null,"supplierGroupCode":183,"group":null,"extraBedCount":null,"bedTypes":null,"adult":2,"groupCode":175,"shortCode":"ArabianOryx","isCache":false,"reprice":"R","roomTypeCode":null,"rateType":"Non Refundable","minStay":null,"price":{"supplierGross":634.19,"supplierTax":142.69,"currency":null,"net":776.88,"isExclusiveRate":false,"supplierCommission":0,"commission":0,"discount":null,"promotions":null,"priceBreakdownRules":null,"supplierNet":776.88,"gross":634.19,"taxType":null,"extraBedPrice":0,"isB2C":false,"isPackage":false,"isDynamic":false,"supplierCurrency":"AED","supplierExtraBedPrice":0,"tax":142.69},"remarks":{"remark":[{"type":"Inclusion","text":"BREAKFAST,COFFEE & TEA,FREE WIFI,DRINKING WATER"},{"text":"Type : AtProperty, Description : Tourism Dirham Fee, Price : 10.88, Currency : USD.","type":"Supplements"}]},"children":null,"marriageIdentifier":18318,"mealCode":"BB","status":"Available","roomIndex":46,"mealDescription":"Break Fast included","inclusions":[{"text":"BREAKFAST,COFFEE & TEA,FREE WIFI,DRINKING WATER","type":"Inclusion"}],"roomCombinationId":18318,"roomName":"Standard Twin Room","isPriceBreakupAvailable":true,"roomIdentifier":2,"rateKey":"1082519!TB!19!TB!84df4dff-fc73-11f0-822a-b62521cc9858!TB!N!TB!AFF!|2O","hotelCode":null,"meal":"Bed and Breakfast","sMeal":"BreakFast","contractType":"O","isCancelationPolicyAvailble":true,"policies":null},{"roomCombinationId":18319,"group":null,"children":null,"roomName":"Standard Double Room, 1 Double Bed,NonSmoking","remarks":{"remark":[{"text":"Free breakfast","type":"Inclusion"},{"type":"Supplements","text":"Type : AtProperty, Description : mandatory_tax, Price : 20.0, Currency : AED."}]},"adult":2,"marriageIdentifier":18319,"sMeal":"BreakFast","rateKey":"1082519!TB!15!TB!84df4dff-fc73-11f0-822a-b62521cc9858!TB!N!TB!AFF!|1O","price":{"supplierExtraBedPrice":0,"net":815.33,"tax":163.35,"isDynamic":false,"supplierCurrency":"AED","supplierGross":651.99,"supplierTax":163.35,"supplierNet":815.33,"supplierCommission":0,"currency":null,"gross":651.99,"taxType":null,"commission":0,"discount":null,"extraBedPrice":0,"isB2C":false,"isPackage":false,"promotions":null,"priceBreakdownRules":null,"isExclusiveRate":false},"roomIndex":27,"roomTypeCode":null,"meal":"Bed and Breakfast","status":"Available","shortCode":"ArabianOryx","isCancelationPolicyAvailble":true,"roomIdentifier":1,"mealCode":"BB","contractType":"O","isCache":false,"reprice":"R","bedTypes":null,"spHotelCode":null,"mealDescription":"Break Fast included","rateType":"Non Refundable","groupCode":175,"minStay":null,"guests":null,"isPriceBreakupAvailable":true,"policies":null,"hotelCode":null,"supplierGroupCode":183,"extraBedCount":null,"inclusions":[{"type":"Inclusion","text":"Free breakfast"}]},{"hotelCode":null,"extraBedCount":null,"roomTypeCode":null,"rateType":"Non Refundable","inclusions":[{"type":"Inclusion","text":"Free breakfast"}],"remarks":{"remark":[{"type":"Inclusion","text":"Free breakfast"},{"type":"Supplements","text":"Type : AtProperty, Description : mandatory_tax, Price : 20.0, Currency : AED."}]},"roomIndex":28,"adult":2,"reprice":"R","isPriceBreakupAvailable":true,"roomCombinationId":18320,"mealCode":"BB","contractType":"O","groupCode":175,"isCache":false,"policies":null,"price":{"commission":0,"isPackage":false,"supplierGross":651.99,"supplierCommission":0,"currency":null,"discount":null,"extraBedPrice":0,"isB2C":false,"isExclusiveRate":false,"promotions":null,"supplierCurrency":"AED","supplierTax":163.35,"supplierNet":815.33,"gross":651.99,"net":815.33,"tax":163.35,"taxType":null,"priceBreakdownRules":null,"supplierExtraBedPrice":0,"isDynamic":false},"guests":null,"isCancelationPolicyAvailble":true,"children":null,"roomName":"Standard Room, 2 Twin Beds,NonSmoking","meal":"Bed and Breakfast","status":"Available","supplierGroupCode":183,"shortCode":"ArabianOryx","minStay":null,"group":null,"roomIdentifier":1,"spHotelCode":null,"marriageIdentifier":18320,"sMeal":"BreakFast","mealDescription":"Break Fast included","rateKey":"1082519!TB!3!TB!84df4dff-fc73-11f0-822a-b62521cc9858!TB!N!TB!AFF!|1O","bedTypes":null},{"hotelCode":null,"roomCombinationId":18319,"isCache":false,"isPriceBreakupAvailable":true,"isCancelationPolicyAvailble":true,"remarks":{"remark":[{"type":"Inclusion","text":"Free breakfast"},{"type":"Supplements","text":"Type : AtProperty, Description : mandatory_tax, Price : 20.0, Currency : AED."}]},"children":null,"spHotelCode":null,"shortCode":"ArabianOryx","group":null,"policies":null,"roomIdentifier":2,"roomName":"Standard Double Room, 1 Double Bed,NonSmoking","status":"Available","groupCode":175,"roomIndex":47,"adult":2,"supplierGroupCode":183,"inclusions":[{"type":"Inclusion","text":"Free breakfast"}],"price":{"taxType":null,"commission":0,"isB2C":false,"supplierCurrency":"AED","supplierExtraBedPrice":0,"promotions":null,"priceBreakdownRules":null,"supplierGross":651.99,"supplierTax":163.35,"supplierCommission":0,"currency":null,"gross":651.99,"tax":163.35,"supplierNet":815.33,"discount":null,"extraBedPrice":0,"isPackage":false,"isDynamic":false,"isExclusiveRate":false,"net":815.33},"guests":null,"meal":"Bed and Breakfast","rateKey":"1082519!TB!15!TB!84df4dff-fc73-11f0-822a-b62521cc9858!TB!N!TB!AFF!|2O","reprice":"R","roomTypeCode":null,"mealDescription":"Break Fast included","contractType":"O","minStay":null,"marriageIdentifier":18319,"mealCode":"BB","sMeal":"BreakFast","extraBedCount":null,"bedTypes":null,"rateType":"Non Refundable"},{"children":null,"meal":"Bed and Breakfast","mealDescription":"Break Fast included","shortCode":"ArabianOryx","reprice":"R","isCancelationPolicyAvailble":true,"sMeal":"BreakFast","rateKey":"1082519!TB!3!TB!84df4dff-fc73-11f0-822a-b62521cc9858!TB!N!TB!AFF!|2O","minStay":null,"group":null,"bedTypes":null,"roomIndex":48,"roomIdentifier":2,"guests":null,"contractType":"O","roomTypeCode":null,"roomName":"Standard Room, 2 Twin Beds,NonSmoking","mealCode":"BB","rateType":"Non Refundable","supplierGroupCode":183,"hotelCode":null,"spHotelCode":null,"marriageIdentifier":18320,"extraBedCount":null,"price":{"priceBreakdownRules":null,"supplierGross":651.99,"supplierNet":815.33,"currency":null,"taxType":null,"extraBedPrice":0,"supplierCurrency":"AED","supplierTax":163.35,"supplierExtraBedPrice":0,"net":815.33,"commission":0,"discount":null,"isPackage":false,"isDynamic":false,"supplierCommission":0,"gross":651.99,"tax":163.35,"isB2C":false,"isExclusiveRate":false,"promotions":null},"remarks":{"remark":[{"type":"Inclusion","text":"Free breakfast"},{"type":"Supplements","text":"Type : AtProperty, Description : mandatory_tax, Price : 20.0, Currency : AED."}]},"roomCombinationId":18320,"groupCode":175,"status":"Available","inclusions":[{"type":"Inclusion","text":"Free breakfast"}],"adult":2,"isCache":false,"isPriceBreakupAvailable":true,"policies":null}],"gross":null,"net":null,"tax":null,"taxType":null},"spHotelCode":null,"name":"ibis World Trade Centre Dubai","groupCode":null,"supplierGroupCode":null}},"contentType":"application/json; charset=utf-8","duration":2483911792},"logId":""}